{"_id":"59ca264786f77445a80ed044","traderId":"54cb50c76803fa8b248b4571","location":"any","image":"/files/quest/icon/5979f91c86f77402996bf9c2.jpg","type":"Elimination","isKey":false,"restartable":false,"instantComplete":false,"secretQuest":false,"min_level":1,"canShowNotificationsInGame":true,"rewards":{"Started":[],"Success":[{"value":"19000","id":"5c94f23786f7743285178ac3","type":"Experience","index":0},{"target":"54cb50c76803fa8b248b4571","value":"0.12","type":"TraderStanding","index":1,"id":"5bcf140286f7742ce2243a42"},{"target":"60971d1356b3517a665d84c0","value":"1","unknown":true,"id":"59ca28c986f77445ac1da7ba","type":"Item","index":2,"items":[{"_id":"60971d1356b3517a665d84c0","_tpl":"5447a9cd4bdc2dbd208b4567","parentId":"hideout","slotId":"hideout","upd":{"StackObjectsCount":1}},{"_id":"60971d1356b3517a665d84c1","_tpl":"571659bb2459771fb2755a12","parentId":"60971d1356b3517a665d84c0","slotId":"mod_pistol_grip"},{"_id":"60971d1356b3517a665d84c2","_tpl":"55802d5f4bdc2dac148b458e","parentId":"60971d1356b3517a665d84c0","slotId":"mod_magazine"},{"_id":"60971d1356b3517a665d84c3","_tpl":"55d355e64bdc2d962f8b4569","parentId":"60971d1356b3517a665d84c0","slotId":"mod_reciever"},{"_id":"60971d1356b3517a665d84c4","_tpl":"5649be884bdc2d79388b4577","parentId":"60971d1356b3517a665d84c0","slotId":"mod_stock"},{"_id":"60971d1356b3517a665d84c5","_tpl":"56ea7165d2720b6e518b4583","parentId":"60971d1356b3517a665d84c0","slotId":"mod_charge"},{"_id":"60971d1356b3517a665d84c6","_tpl":"54527a984bdc2d4e668b4567","parentId":"60971d1356b3517a665d84c2","slotId":"cartridges","location":0,"upd":{"StackObjectsCount":30}},{"_id":"60971d1356b3517a665d84c7","_tpl":"57aca93d2459771f2c7e26db","parentId":"60971d1356b3517a665d84c3","slotId":"mod_scope"},{"_id":"60971d1356b3517a665d84c8","_tpl":"55d35ee94bdc2d61338b4568","parentId":"60971d1356b3517a665d84c3","slotId":"mod_barrel"},{"_id":"60971d1356b3517a665d84c9","_tpl":"55f84c3c4bdc2d5f408b4576","parentId":"60971d1356b3517a665d84c3","slotId":"mod_handguard"},{"_id":"60971d1356b3517a665d84ca","_tpl":"58d2946386f774496974c37e","parentId":"60971d1356b3517a665d84c4","slotId":"mod_stock_000"},{"_id":"60971d1356b3517a665d84cb","_tpl":"56ea8180d2720bf2698b456a","parentId":"60971d1356b3517a665d84c8","slotId":"mod_muzzle"},{"_id":"60971d1356b3517a665d84cc","_tpl":"56eabcd4d2720b66698b4574","parentId":"60971d1356b3517a665d84c8","slotId":"mod_gas_block"},{"_id":"60971d1356b3517a665d84cd","_tpl":"58c157be86f77403c74b2bb6","parentId":"60971d1356b3517a665d84c9","slotId":"mod_foregrip"},{"_id":"60971d1356b3517a665d84ce","_tpl":"5649a2464bdc2d91118b45a8","parentId":"60971d1356b3517a665d84c9","slotId":"mod_scope"},{"_id":"60971d1356b3517a665d84cf","_tpl":"57d17e212459775a1179a0f5","parentId":"60971d1356b3517a665d84c9","slotId":"mod_tactical002"},{"_id":"60971d1356b3517a665d84d0","_tpl":"544909bb4bdc2d6f028b4577","parentId":"60971d1356b3517a665d84c9","slotId":"mod_tactical"},{"_id":"60971d1356b3517a665d84d1","_tpl":"57da93632459771cb65bf83f","parentId":"60971d1356b3517a665d84cb","slotId":"mod_muzzle"},{"_id":"60971d1356b3517a665d84d2","_tpl":"58d39d3d86f77445bb794ae7","parentId":"60971d1356b3517a665d84ce","slotId":"mod_scope"},{"_id":"60971d1356b3517a665d84d3","_tpl":"57d17c5e2459775a5c57d17d","parentId":"60971d1356b3517a665d84cf","slotId":"mod_flashlight"},{"_id":"60971d1356b3517a665d84d4","_tpl":"58d399e486f77442e0016fe7","parentId":"60971d1356b3517a665d84d2","slotId":"mod_scope"},{"_id":"60971d1356b3517a665d84d5","_tpl":"58d2912286f7744e27117493","parentId":"60971d1356b3517a665d84ca","slotId":"mod_stock"}]},{"target":"60971d1356b3517a665d84d6","value":"100000","id":"5a2fb31686f774769732daa6","type":"Item","index":3,"items":[{"_id":"60971d1356b3517a665d84d6","_tpl":"5449016a4bdc2d6f028b456f","upd":{"StackObjectsCount":100000}}]},{"target":"60971d1356b3517a665d84d7","id":"5ac65f9486f774066f04bd32","type":"AssortmentUnlock","index":4,"loyaltyLevel":3,"traderId":"54cb50c76803fa8b248b4571","items":[{"_id":"60971d1356b3517a665d84d7","_tpl":"56dff061d2720bb5668b4567"}]},{"target":"5c0647fdd443bc2504c2d371","value":"-0.01","id":"5d6e716286f7743b5f001113","type":"TraderStanding","index":5}],"Fail":[]},"conditions":{"AvailableForStart":[{"_parent":"Level","_props":{"compareMethod":">=","value":"20","index":0,"parentId":"","id":"59a926b186f774753c5479a2"}}],"AvailableForFinish":[{"_parent":"CounterCreator","_props":{"value":"10","type":"Elimination","counter":{"id":"59674d5186f77446b879d5f6","conditions":[{"_parent":"Kills","_props":{"target":"Savage","compareMethod":">=","value":"1","weapon":["5a7828548dc32e5a9c28b516","576165642459773c7a400233","56dee2bdd2720bc8328b4567","5580223e4bdc2d1c128b457f","54491c4f4bdc2db1078b4568","5e870397991fd70db46995c8"],"id":"59674d5586f77446b62354e7"}},{"_parent":"Location","_props":{"target":["Woods"],"id":"59ca279086f77445ab365c84"}}]},"index":0,"parentId":"","id":"59674d5986f77446b872d5f7"}},{"_parent":"CounterCreator","_props":{"value":"10","type":"Elimination","counter":{"id":"59ca27f786f77445aa0ddc13","conditions":[{"_parent":"Kills","_props":{"target":"AnyPmc","compareMethod":">=","value":"1","id":"59ca280186f77445ac1da7b9"}},{"_parent":"Location","_props":{"target":["Shoreline"],"id":"59ca280886f77445a80ed045"}},{"_parent":"Equipment","_props":{"equipmentInclusive":[["572b7adb24597762ae139821"],["572b7f1624597762ae139822"],["5b432f3d5acfc4704b4a1dfb"],["5ab8f4ff86f77431c60d91ba"],["5ab8f39486f7745cd93a1cca"]],"id":"5c922b6486f77438522e0c35"}}]},"index":1,"parentId":"","id":"59ca27f786f77445aa0ddc14"}},{"_parent":"FindItem","_props":{"target":["57e26fc7245977162a14b800"],"value":"5","minDurability":0,"index":2,"parentId":"","id":"59ca293c86f91445a80ed047","maxDurability":0,"dogtagLevel":0,"onlyFoundInRaid":true,"resetOnSessionEnd":false}},{"_parent":"HandoverItem","_props":{"target":["57e26fc7245977162a14b800"],"value":"5","minDurability":0,"index":3,"parentId":"","id":"59ca29ab86f77445ab431c86","visibilityConditions":[],"maxDurability":0,"dogtagLevel":0,"onlyFoundInRaid":true}}],"Fail":[]}}