{"_id":"5e381b0286f77420e3417a74","traderId":"5ac3b934156ae10c4430e83c","location":"any","image":"/files/quest/icon/5e4d3a5886f77438b1632d82.jpg","type":"PickUp","isKey":false,"restartable":false,"instantComplete":false,"secretQuest":false,"min_level":0,"canShowNotificationsInGame":true,"rewards":{"Started":[],"Success":[{"target":"60971d1356b3517a665d877f","value":"100000","id":"5e58de2886f7747c295d2898","type":"Item","index":0,"items":[{"_id":"60971d1356b3517a665d877f","_tpl":"5449016a4bdc2d6f028b456f","upd":{"StackObjectsCount":100000}}]}],"Fail":[]},"conditions":{"AvailableForStart":[{"_parent":"TraderLoyalty","_props":{"target":"5ac3b934156ae10c4430e83c","compareMethod":">=","value":"4","index":0,"parentId":"","id":"5e58dabd86f7747c27218702"}},{"_parent":"Quest","_props":{"target":"5ae4497b86f7744cf402ed00","status":[4],"availableAfter":0,"index":1,"parentId":"","id":"5e58dace86f7747c295d2893"}}],"AvailableForFinish":[{"_parent":"FindItem","_props":{"target":["5e2af4d286f7746d4159f07a"],"value":"5","minDurability":0,"maxDurability":0,"dogtagLevel":0,"onlyFoundInRaid":true,"index":0,"parentId":"","id":"5e38261886f77429853af26c"}},{"_parent":"HandoverItem","_props":{"target":["5e2af4d286f7746d4159f07a"],"value":"5","minDurability":0,"maxDurability":0,"dogtagLevel":0,"onlyFoundInRaid":true,"index":1,"parentId":"","id":"5e382fef86f7741e53790d40"}},{"_parent":"FindItem","_props":{"target":["5e2af4a786f7746d3f3c3400"],"value":"10","minDurability":0,"maxDurability":0,"dogtagLevel":0,"onlyFoundInRaid":true,"index":2,"parentId":"","id":"5e382b6986f7741b72695045"}},{"_parent":"HandoverItem","_props":{"target":["5e2af4a786f7746d3f3c3400"],"value":"10","minDurability":0,"maxDurability":0,"dogtagLevel":0,"onlyFoundInRaid":true,"index":3,"parentId":"","id":"5e38356d86f7742993306cac"}},{"_parent":"FindItem","_props":{"target":["5c12688486f77426843c7d32"],"value":"3","minDurability":0,"maxDurability":0,"dogtagLevel":0,"onlyFoundInRaid":true,"index":4,"parentId":"","id":"5e382d6386f77429a01f82fb"}},{"_parent":"HandoverItem","_props":{"target":["5c12688486f77426843c7d32"],"value":"3","minDurability":0,"maxDurability":0,"dogtagLevel":0,"onlyFoundInRaid":true,"index":5,"parentId":"","id":"5e3835e886f77429910d4465"}}],"Fail":[]}}