{"_id":"5e4d515e86f77438b2195244","traderId":"5ac3b934156ae10c4430e83c","location":"any","image":"/files/quest/icon/5e4d3a5186f77464185227f3.jpg","type":"PickUp","isKey":false,"restartable":false,"instantComplete":false,"secretQuest":false,"min_level":0,"canShowNotificationsInGame":true,"rewards":{"Started":[],"Success":[{"target":"6058f892295158067b2ba3b8","value":"100000","id":"5e58ddad86f7747c2639ee44","type":"Item","index":0,"items":[{"_id":"6058f892295158067b2ba3b8","_tpl":"5449016a4bdc2d6f028b456f","upd":{"StackObjectsCount":100000}}]},{"target":"6058f892295158067b2ba3b9","value":"1","id":"5e58e25786f7740bef574f07","type":"Item","index":1,"items":[{"_id":"6058f892295158067b2ba3b9","_tpl":"5c0e774286f77468413cc5b2","upd":{"StackObjectsCount":1}}]}],"Fail":[]},"conditions":{"AvailableForStart":[{"_parent":"Quest","_props":{"target":"5e383a6386f77465910ce1f3","status":[4],"availableAfter":0,"index":0,"parentId":"","id":"5e58dd9086f7747c2639ee43"}}],"AvailableForFinish":[{"_parent":"FindItem","_props":{"target":["5e2af47786f7746d404f3aaa"],"value":"10","minDurability":0,"maxDurability":0,"dogtagLevel":0,"onlyFoundInRaid":true,"index":0,"parentId":"","id":"5e4d515e86f77438b2195245"}},{"_parent":"HandoverItem","_props":{"target":["5e2af47786f7746d404f3aaa"],"value":"10","minDurability":0,"maxDurability":0,"dogtagLevel":0,"onlyFoundInRaid":true,"index":1,"parentId":"","id":"5e4d515e86f77438b2195246"}},{"_parent":"FindItem","_props":{"target":["5e2af41e86f774755a234b67"],"value":"10","minDurability":0,"maxDurability":0,"dogtagLevel":0,"onlyFoundInRaid":true,"index":2,"parentId":"","id":"5e4d515e86f77438b2195247"}},{"_parent":"HandoverItem","_props":{"target":["5e2af41e86f774755a234b67"],"value":"10","minDurability":0,"maxDurability":0,"dogtagLevel":0,"onlyFoundInRaid":true,"index":3,"parentId":"","id":"5e4d515e86f77438b2195248"}},{"_parent":"FindItem","_props":{"target":["5e2af29386f7746d4159f077"],"value":"5","minDurability":0,"maxDurability":0,"dogtagLevel":0,"onlyFoundInRaid":true,"index":4,"parentId":"","id":"5e4d515e86f77438b2195249"}},{"_parent":"HandoverItem","_props":{"target":["5e2af29386f7746d4159f077"],"value":"5","minDurability":0,"maxDurability":0,"dogtagLevel":0,"onlyFoundInRaid":true,"index":5,"parentId":"","id":"5e4d515e86f77438b219524a"}}],"Fail":[]}}