{"_id":"5edab736cc183c769d778bc2","traderId":"54cb57776803fa99248b456e","location":"5704e554d2720bac5b8b456e","image":"/files/quest/icon/59c2742286f77475ec568d92.jpg","type":"Discover","isKey":false,"restartable":false,"instantComplete":false,"secretQuest":false,"min_level":19,"canShowNotificationsInGame":true,"rewards":{"Started":[],"Success":[{"value":"12600","id":"5f0d99c931015e1bd32bd36f","type":"Experience","index":0},{"target":"54cb57776803fa99248b456e","value":"0.08","id":"5f0d9b256f25345edd40dc08","type":"TraderStanding","index":1},{"target":"60971d1356b3517a665d8793","value":"45000","id":"5f0d99e04178576c5352c046","type":"Item","index":2,"items":[{"_id":"60971d1356b3517a665d8793","_tpl":"5449016a4bdc2d6f028b456f","upd":{"StackObjectsCount":45000}}]}],"Fail":[]},"conditions":{"AvailableForStart":[{"_parent":"Level","_props":{"compareMethod":">=","value":"21","index":0,"parentId":"","id":"5edababacecc0069284c0ec7"}},{"_parent":"Quest","_props":{"target":"596a1e6c86f7741ddc2d3206","status":[4],"availableAfter":0,"index":1,"parentId":"","id":"5f104af087fa885f9d696bed"}}],"AvailableForFinish":[{"_parent":"CounterCreator","_props":{"value":"1","type":"Discover","doNotResetIfCounterCompleted":false,"oneSessionOnly":true,"counter":{"id":"5edab7d3cc183c769d778bc4","conditions":[{"_parent":"VisitPlace","_props":{"target":"ter_023_area_1_1","value":"1","id":"5edab8410880da21347b3823"}}]},"index":0,"parentId":"","id":"5edab7d3cc183c769d778bc5"}},{"_parent":"CounterCreator","_props":{"value":"1","type":"Discover","doNotResetIfCounterCompleted":false,"oneSessionOnly":true,"counter":{"id":"5edab8890880da21347b3825","conditions":[{"_parent":"VisitPlace","_props":{"target":"ter_023_area_3_1","value":"1","id":"5edab8aad143ed1d6378d123"}}]},"index":1,"parentId":"","id":"5edab8890880da21347b3826"}},{"_parent":"CounterCreator","_props":{"value":"1","type":"Discover","doNotResetIfCounterCompleted":false,"oneSessionOnly":true,"counter":{"id":"5edab8e216d985118871ba17","conditions":[{"_parent":"VisitPlace","_props":{"target":"ter_023_area_2_1","value":"1","id":"5edab8f77869412e9c669c24"}}]},"index":2,"parentId":"","id":"5edab8e216d985118871ba18"}},{"_parent":"CounterCreator","_props":{"value":"1","type":"Completion","doNotResetIfCounterCompleted":false,"oneSessionOnly":true,"counter":{"id":"5f03969a51823847c253af9f","conditions":[{"_parent":"ExitStatus","_props":{"status":["Survived","Runner"],"id":"5f0396babb4e27377c090ced"}},{"_parent":"Location","_props":{"target":["Shoreline"],"id":"5f039d425ab21175a70122e2"}}]},"index":3,"parentId":"","id":"5f03969a51823847c253afa0","visibilityConditions":[]}}],"Fail":[]}}